mariekondo/__init__.py
mariekondo/cleaning_functions.py
mariekondo/test/test_cleaning_functions.py
mariekondo-0.0.3.dist-info/METADATA
mariekondo-0.0.3.dist-info/WHEEL
mariekondo-0.0.3.dist-info/top_level.txt
mariekondo-0.0.3.dist-info/RECORD
