Metadata-Version: 2.1
Name: mariekondo
Version: 0.0.3
Author: James Baker
Author-email: james@talentium.io
License: MIT
Classifier: Programming Language :: Python :: 3
Classifier: License :: OSI Approved :: MIT License
Classifier: Operating System :: OS Independent
Requires-Dist: searchdatamodels ==0.0.19
